{
  "dmg+5": {
    "title": "§f弄 §6+5% §7Daño infligido por §cVaazkar",
    "frame": {
      "type": "texture",
      "data": {
        "unlocked": "prominent_talents:textures/frames/diamond_selected.png",
        "available": "prominent_talents:textures/frames/diamond.png"
      }
    },
    "icon": {
      "type": "texture",
      "data": {
        "texture": "simplyskills:textures/icons/prom_compat/fire.png"
      }
    },
    "rewards": [
      {
        "type": "puffish_skills:attribute",
        "data": {
          "attribute": "prominent:artifact_damage",
          "value": 0.05,
          "operation": "addition"
        }
      }
    ],
    "editor-color": "#ff00a6",
    "metadata": {
      "icon": "bkuisnsd4bko11eg"
    }
  },
  "health+5": {
    "title": "§f牢 §c+5% §7Salud Máxima",
    "frame": {
      "type": "texture",
      "data": {
        "unlocked": "prominent_talents:textures/frames/diamond_selected.png",
        "available": "prominent_talents:textures/frames/diamond.png"
      }
    },
    "icon": {
      "type": "texture",
      "data": {
        "texture": "simplyskills:textures/icons/prom_compat/health.png"
      }
    },
    "rewards": [
      {
        "type": "puffish_skills:attribute",
        "data": {
          "attribute": "generic.max_health",
          "value": 0.05,
          "operation": "multiply_base"
        }
      }
    ],
    "editor-color": "#ff00a6",
    "metadata": {
      "icon": "vt5q3v2tr9v4ow8e"
    }
  },
  "phase+tank": {
    "title": "§f鹿 §6Fuego Instantáneo",
    "description": "§cReemplaza Muro de Llama\n\n§7Canaliza las llamas que residen en tu interior, haciendo que Muro de Llama se Inicie instantáneamente después de realizar Bloqueo, y reduciendo su Enfriamiento a 10 Segundos.\n\n§e牢 §c+20 §7Reabsorción",
    "size": 1.5,
    "frame": {
      "type": "texture",
      "data": {
        "unlocked": "prominent_talents:textures/frames/diamond_selected.png",
        "available": "prominent_talents:textures/frames/diamond.png"
      }
    },
    "icon": {
      "type": "texture",
      "data": {
        "texture": "prominent:textures/item/artifacts/vaazkar/vaazkar_item.png"
      }
    },
    "rewards": [
      {
        "type": "puffish_skills:attribute",
        "data": {
          "attribute": "prominent:artifact_phase",
          "value": 1,
          "operation": "addition"
        }
      },
      {
        "type": "puffish_skills:attribute",
        "data": {
          "attribute": "extraspellattributes:reabsorption",
          "value": 20,
          "operation": "addition"
        }
      }
    ],
    "metadata": {
      "icon": "n241yslto644cv8k"
    }
  },
  "phase+support": {
    "title": "§f鹿 §6Fuegos Protectores",
    "description": "§cReemplaza Muro de Llama\n\n§7Las Llamas canalizadas por tu Muro de Llama ya no infligen Daño a los enemigos, sino que curan a los Jugadores cercanos por el 3% de tu Salud Máxima.\n\n§f綾 §e+5§7 Poder Sagrado",
    "size": 1.5,
    "frame": {
      "type": "texture",
      "data": {
        "unlocked": "prominent_talents:textures/frames/diamond_selected.png",
        "available": "prominent_talents:textures/frames/diamond.png"
      }
    },
    "icon": {
      "type": "texture",
      "data": {
        "texture": "prominent:textures/item/artifacts/vaazkar/vaazkar_item.png"
      }
    },
    "rewards": [
      {
        "type": "puffish_skills:attribute",
        "data": {
          "attribute": "prominent:artifact_phase",
          "value": 2,
          "operation": "addition"
        }
      },
      {
        "type": "puffish_skills:attribute",
        "data": {
          "attribute": "spell_power:healing",
          "value": 5,
          "operation": "addition"
        }
      }
    ],
    "metadata": {
      "icon": "znbglilmbdnzro1x"
    }
  },
  "phase+bruiser": {
    "title": "§f鹿 §6Tormenta Ígnea",
    "description": "§cReemplaza Muro de Llama\n\n§7Desata el Muro de Llama, provocando una Tormenta de fuego que inflige un 5% de daño máximo de Salud por segundo, con un tamaño Doble.\n\n§fꦘ §9+20§7 Corrupción",
    "size": 1.5,
    "frame": {
      "type": "texture",
      "data": {
        "unlocked": "prominent_talents:textures/frames/diamond_selected.png",
        "available": "prominent_talents:textures/frames/diamond.png"
      }
    },
    "icon": {
      "type": "texture",
      "data": {
        "texture": "prominent:textures/item/artifacts/vaazkar/vaazkar_item.png"
      }
    },
    "rewards": [
      {
        "type": "puffish_skills:attribute",
        "data": {
          "attribute": "eldritch_end:corruption",
          "value": 20,
          "operation": "addition"
        }
      },
      {
        "type": "puffish_skills:attribute",
        "data": {
          "attribute": "prominent:artifact_phase",
          "value": 3,
          "operation": "addition"
        }
      }
    ],
    "metadata": {
      "icon": "eqvex0gqoc0c3krb"
    }
  }
}